CpythonGeiDaxueshengDeRumenjiaocheng/README.md
CpythonGeiDaxueshengDeRumenjiaocheng/__init__.py
CpythonGeiDaxueshengDeRumenjiaocheng/__main__.py
CpythonGeiDaxueshengDeRumenjiaocheng/file.epub
CpythonGeiDaxueshengDeRumenjiaocheng/index.html
CpythonGeiDaxueshengDeRumenjiaocheng/css/__init__.py
CpythonGeiDaxueshengDeRumenjiaocheng/css/annotations.css
CpythonGeiDaxueshengDeRumenjiaocheng/css/main.css
CpythonGeiDaxueshengDeRumenjiaocheng/css/normalize.css
CpythonGeiDaxueshengDeRumenjiaocheng/css/popup.css
CpythonGeiDaxueshengDeRumenjiaocheng/font/__init__.py
CpythonGeiDaxueshengDeRumenjiaocheng/font/fontello.eot
CpythonGeiDaxueshengDeRumenjiaocheng/font/fontello.svg
CpythonGeiDaxueshengDeRumenjiaocheng/font/fontello.ttf
CpythonGeiDaxueshengDeRumenjiaocheng/font/fontello.woff
CpythonGeiDaxueshengDeRumenjiaocheng/img/__init__.py
CpythonGeiDaxueshengDeRumenjiaocheng/img/annotator-glyph-sprite.png
CpythonGeiDaxueshengDeRumenjiaocheng/img/annotator-icon-sprite.png
CpythonGeiDaxueshengDeRumenjiaocheng/img/apple-touch-icon.png
CpythonGeiDaxueshengDeRumenjiaocheng/img/cancelfullscreen.png
CpythonGeiDaxueshengDeRumenjiaocheng/img/close.png
CpythonGeiDaxueshengDeRumenjiaocheng/img/fullscreen.png
CpythonGeiDaxueshengDeRumenjiaocheng/img/loader.gif
CpythonGeiDaxueshengDeRumenjiaocheng/img/menu-icon.png
CpythonGeiDaxueshengDeRumenjiaocheng/img/save.png
CpythonGeiDaxueshengDeRumenjiaocheng/img/saved.png
CpythonGeiDaxueshengDeRumenjiaocheng/img/settings-s.png
CpythonGeiDaxueshengDeRumenjiaocheng/img/settings.png
CpythonGeiDaxueshengDeRumenjiaocheng/img/star.png
CpythonGeiDaxueshengDeRumenjiaocheng/js/__init__.py
CpythonGeiDaxueshengDeRumenjiaocheng/js/epub.js
CpythonGeiDaxueshengDeRumenjiaocheng/js/epub.min.js
CpythonGeiDaxueshengDeRumenjiaocheng/js/epub.min.map
CpythonGeiDaxueshengDeRumenjiaocheng/js/hooks.min.js
CpythonGeiDaxueshengDeRumenjiaocheng/js/hooks.min.map
CpythonGeiDaxueshengDeRumenjiaocheng/js/reader.js
CpythonGeiDaxueshengDeRumenjiaocheng/js/reader.js.map
cpython_gei_daxuesheng_de_rumenjiaocheng-2024.3.5.0.dist-info/METADATA
cpython_gei_daxuesheng_de_rumenjiaocheng-2024.3.5.0.dist-info/WHEEL
cpython_gei_daxuesheng_de_rumenjiaocheng-2024.3.5.0.dist-info/entry_points.txt
cpython_gei_daxuesheng_de_rumenjiaocheng-2024.3.5.0.dist-info/top_level.txt
cpython_gei_daxuesheng_de_rumenjiaocheng-2024.3.5.0.dist-info/RECORD
